LICENSE
MANIFEST.in
README.md
setup.py
datacleaner/__init__.py
datacleaner/_version.py
datacleaner/datacleaner.py
datacleaner.egg-info/PKG-INFO
datacleaner.egg-info/SOURCES.txt
datacleaner.egg-info/dependency_links.txt
datacleaner.egg-info/entry_points.txt
datacleaner.egg-info/requires.txt
datacleaner.egg-info/top_level.txt
datacleaner.egg-info/zip-safe