Metadata-Version: 1.1
Name: datacleaner
Version: 0.1.5
Summary: A Python tool that automatically cleans data sets and readies them for analysis.
Home-page: https://github.com/rhiever/datacleaner
Author: Randal S. Olson
Author-email: rso@randalolson.com
License: License :: OSI Approved :: MIT License
Keywords: data cleaning,csv,machine learning,data analysis,data engineering
Platform: UNKNOWN
Classifier: Intended Audience :: Developers
Classifier: Intended Audience :: Information Technology
Classifier: Intended Audience :: Science/Research
Classifier: License :: OSI Approved :: MIT License
Classifier: Programming Language :: Python :: 2
Classifier: Programming Language :: Python :: 2.7
Classifier: Programming Language :: Python :: 3
Classifier: Programming Language :: Python :: 3.4
Classifier: Programming Language :: Python :: 3.5
Classifier: Topic :: Utilities
